lightfly/__init__.py
lightfly/exception.py
lightfly/fund.py
lightfly/http.py
lightfly/stock.py
tests/__init__.py
tests/fund_test.py
tests/stock_test.py
lightfly-0.1.6.dist-info/LICENSE
lightfly-0.1.6.dist-info/METADATA
lightfly-0.1.6.dist-info/WHEEL
lightfly-0.1.6.dist-info/top_level.txt
lightfly-0.1.6.dist-info/RECORD
